README.md
setup.py
rosey_sim/__init__.py
rosey_sim/sensitivity.py
rosey_sim.egg-info/PKG-INFO
rosey_sim.egg-info/SOURCES.txt
rosey_sim.egg-info/dependency_links.txt
rosey_sim.egg-info/not-zip-safe
rosey_sim.egg-info/requires.txt
rosey_sim.egg-info/top_level.txt
tests/__init__.py
tests/test_sensitivity.py