Metadata-Version: 1.1
Name: rosey-sim
Version: 0.20200616
Summary: Causal, Probabilistic and Uncertainty Simulations
Home-page: https://github.com/arose13/rosey-sim
Author: Stephen Rose
Author-email: me@stephenro.se
License: BSD
Platform: UNKNOWN
Classifier: Development Status :: 4 - Beta
Classifier: Intended Audience :: Developers
Classifier: Programming Language :: Python :: 3
Classifier: Topic :: Scientific/Engineering :: Artificial Intelligence
